quadfeather/__init__.py
quadfeather/add_sidecars.py
quadfeather/demo.py
quadfeather/download.py
quadfeather/ingester.py
quadfeather/test.i
quadfeather/tiler.py
quadfeather-2.3.0rc1.dist-info/METADATA
quadfeather-2.3.0rc1.dist-info/WHEEL
quadfeather-2.3.0rc1.dist-info/entry_points.txt
quadfeather-2.3.0rc1.dist-info/RECORD
