Metadata-Version: 2.4
Name: quadfeather
Version: 2.3.0rc1
Summary: Quadtree tiling from CSV/Apache Arrow for use with deepscatter in the browser.
Requires-Python: >=3.9
Requires-Dist: numpy>=1.22.0
Requires-Dist: pandas>=1.0.0
Requires-Dist: pyarrow>=13.0.0
